ka_uts_path/__init__.py
ka_uts_path/__version__.py
ka_uts_path/file.py
ka_uts_path/path.py
ka_uts_path/pathnm.py
ka_uts_path/py.typed
ka_uts_path-5.0.0.250623.dist-info/licenses/LICENSE.txt
ka_uts_path-5.0.0.250623.dist-info/METADATA
ka_uts_path-5.0.0.250623.dist-info/WHEEL
ka_uts_path-5.0.0.250623.dist-info/top_level.txt
ka_uts_path-5.0.0.250623.dist-info/RECORD
