Metadata-Version: 2.4
Name: ka_uts_path
Version: 5.0.0.250623
Summary: Dictionary Utilities
Author-email: Bernd Stroehle <bernd.stroehle@gmail.com>
Maintainer-email: Bernd Stroehle <bernd.stroehle@gmail.com>
License-Expression: GPL-3.0-only WITH Classpath-exception-2.0 OR BSD-3-Clause
Project-URL: Source Code, https://github.com/bs29/ka_uts_path/tree/master
Project-URL: Homepage, https://kosakya.de/
Project-URL: Documentation, https://ka-apc.readthedocs.io/en/latest
Classifier: Development Status :: 5 - Production/Stable
Classifier: Intended Audience :: Developers
Classifier: Operating System :: OS Independent
Classifier: Programming Language :: Python :: 3.12
Classifier: Natural Language :: English
Classifier: Topic :: Software Development :: Libraries :: Python Modules
Requires-Python: >=3.10
License-File: LICENSE.txt
Requires-Dist: ka_uts_aod>=4.1.0.250525
Requires-Dist: ka_uts_log>=4.1.1.250609
Requires-Dist: ka_uts_obj>=4.1.0.250525
Requires-Dist: ka_uts_uts>=4.1.0.250601
Requires-Dist: pandas>=2.3.0
Dynamic: license-file
